alignak_checks_nginx/__init__.py
alignak_checks_nginx-1.1.3.data/data/share/alignak/etc/arbiter/packs/nginx/commands.cfg
alignak_checks_nginx-1.1.3.data/data/share/alignak/etc/arbiter/packs/nginx/groups.cfg
alignak_checks_nginx-1.1.3.data/data/share/alignak/etc/arbiter/packs/nginx/templates.cfg
alignak_checks_nginx-1.1.3.data/data/share/alignak/etc/backend-json/nginx/commands.json
alignak_checks_nginx-1.1.3.data/data/share/alignak/etc/backend-json/nginx/hostgroups.json
alignak_checks_nginx-1.1.3.data/data/share/alignak/etc/backend-json/nginx/hosts-templates.json
alignak_checks_nginx-1.1.3.data/data/share/alignak/etc/backend-json/nginx/servicegroups.json
alignak_checks_nginx-1.1.3.data/data/share/alignak/etc/backend-json/nginx/services-templates.json
alignak_checks_nginx-1.1.3.data/data/share/alignak/etc/backend-json/nginx/setup.sh
alignak_checks_nginx-1.1.3.data/data/share/alignak/libexec/CHANGELOG
alignak_checks_nginx-1.1.3.data/data/share/alignak/libexec/LICENSE
alignak_checks_nginx-1.1.3.data/data/share/alignak/libexec/README.md
alignak_checks_nginx-1.1.3.data/data/share/alignak/libexec/check_nginx_status.pl
alignak_checks_nginx-1.1.3.data/data/share/alignak/libexec/utils.pm
alignak_checks_nginx-1.1.3.dist-info/LICENSE
alignak_checks_nginx-1.1.3.dist-info/METADATA
alignak_checks_nginx-1.1.3.dist-info/WHEEL
alignak_checks_nginx-1.1.3.dist-info/top_level.txt
alignak_checks_nginx-1.1.3.dist-info/RECORD
